ossdirectory/__init__.py
ossdirectory/clone.py
ossdirectory/fetch.py
ossdirectory/schema.py
resources/__init__.py
resources/schema/blockchain-address.json
resources/schema/collection.json
resources/schema/named.json
resources/schema/project.json
resources/schema/social-profile.json
resources/schema/url.json
oss_directory-0.2.5.dist-info/LICENSE
oss_directory-0.2.5.dist-info/METADATA
oss_directory-0.2.5.dist-info/WHEEL
oss_directory-0.2.5.dist-info/RECORD
