Metadata-Version: 2.1
Name: oss-directory
Version: 0.2.5
Summary: Open source software directory
Home-page: https://www.opensource.observer
License: Apache-2.0
Author: Kariba Labs
Requires-Python: >=3.11,<3.13
Classifier: License :: OSI Approved :: Apache Software License
Classifier: Programming Language :: Python :: 3
Classifier: Programming Language :: Python :: 3.11
Classifier: Programming Language :: Python :: 3.12
Requires-Dist: gitpython (>=3.1.43,<4.0.0)
Requires-Dist: jsonschema (>=4.22.0,<5.0.0)
Requires-Dist: pyyaml (>=6.0.1,<7.0.0)
Requires-Dist: requests (>=2.32.3,<3.0.0)
Requires-Dist: toml (>=0.10.2,<0.11.0)
Project-URL: Documentation, https://docs.opensource.observer/
Project-URL: Repository, https://github.com/opensource-observer/oss-directory
